bishowmath-0.1.0.dist-info/licenses/LICENSE
simplemath/__init__.py
simplemath/operations.py
tests/__init__.py
tests/test_operations.py
bishowmath-0.1.0.dist-info/METADATA
bishowmath-0.1.0.dist-info/WHEEL
bishowmath-0.1.0.dist-info/top_level.txt
bishowmath-0.1.0.dist-info/RECORD
