Metadata-Version: 2.4
Name: bishowmath
Version: 0.1.0
Summary: A simple math library for basic arithmetic
Author: Bishwa Ghimire
Author-email: bishowghi2061.email@example.com
Classifier: Programming Language :: Python :: 3
Classifier: License :: OSI Approved :: MIT License
Classifier: Operating System :: OS Independent
Requires-Python: >=3.6
License-File: LICENSE
Dynamic: author
Dynamic: author-email
Dynamic: classifier
Dynamic: license-file
Dynamic: requires-python
Dynamic: summary
